Metadata-Version: 2.1
Name: cpz
Version: 1.0.1
Summary: A simple xml parse and build library.
Home-page: https://github.com/heronotears/cpz
Author: dbdb
Author-email: <chenpingzhao@gmail.com>
Maintainer: dbdb
License: MIT
Platform: any
Requires-Dist: numpy
